<?xml version="1.0" encoding="UTF-8"?>
<opportunityTypes>
	<opportunityType>
		<name>EMPLOYMENT</name>
	</opportunityType>
	<opportunityType>
		<name>EMPLOYMENT_SECONDMENT</name>
	</opportunityType>
	<opportunityType>
		<name>SCHOLARSHIP_POSTGRADUATE_RESEARCH</name>
	</opportunityType>
	<opportunityType>
		<name>SCHOLARSHIP_POSTGRADUATE_TAUGHT</name>
	</opportunityType>
	<opportunityType>
		<name>SCHOLARSHIP_UNDERGRADUATE</name>
	</opportunityType>
	<opportunityType>
		<name>STUDY_POSTGRADUATE_RESEARCH</name>
	</opportunityType>
	<opportunityType>
		<name>STUDY_POSTGRADUATE_TAUGHT</name>
	</opportunityType>
	<opportunityType>
		<name>STUDY_UNDERGRADUATE</name>
	</opportunityType>
	<opportunityType>
		<name>TRAINING</name>
	</opportunityType>
	<opportunityType>
		<name>VOLUNTEERING</name>
	</opportunityType>
	<opportunityType>
		<name>WORK_EXPERIENCE</name>
	</opportunityType>
</opportunityTypes>
